README.md
libOpenCL.so
libSvtAv1Enc.so
libabsl_bad_any_cast_impl.so
libabsl_bad_optional_access.so
libabsl_bad_variant_access.so
libabsl_base.so
libabsl_city.so
libabsl_civil_time.so
libabsl_cord.so
libabsl_cord_internal.so
libabsl_cordz_functions.so
libabsl_cordz_handle.so
libabsl_cordz_info.so
libabsl_cordz_sample_token.so
libabsl_crc32c.so
libabsl_crc_cord_state.so
libabsl_crc_cpu_detect.so
libabsl_crc_internal.so
libabsl_debugging_internal.so
libabsl_demangle_internal.so
libabsl_die_if_null.so
libabsl_examine_stack.so
libabsl_exponential_biased.so
libabsl_failure_signal_handler.so
libabsl_flags_commandlineflag.so
libabsl_flags_commandlineflag_internal.so
libabsl_flags_config.so
libabsl_flags_internal.so
libabsl_flags_marshalling.so
libabsl_flags_parse.so
libabsl_flags_private_handle_accessor.so
libabsl_flags_program_name.so
libabsl_flags_reflection.so
libabsl_flags_usage.so
libabsl_flags_usage_internal.so
libabsl_graphcycles_internal.so
libabsl_hash.so
libabsl_hashtablez_sampler.so
libabsl_int128.so
libabsl_kernel_timeout_internal.so
libabsl_leak_check.so
libabsl_log_entry.so
libabsl_log_flags.so
libabsl_log_globals.so
libabsl_log_initialize.so
libabsl_log_internal_check_op.so
libabsl_log_internal_conditions.so
libabsl_log_internal_format.so
libabsl_log_internal_globals.so
libabsl_log_internal_log_sink_set.so
libabsl_log_internal_message.so
libabsl_log_internal_nullguard.so
libabsl_log_internal_proto.so
libabsl_log_severity.so
libabsl_log_sink.so
libabsl_low_level_hash.so
libabsl_malloc_internal.so
libabsl_periodic_sampler.so
libabsl_random_distributions.so
libabsl_random_internal_distribution_test_util.so
libabsl_random_internal_platform.so
libabsl_random_internal_pool_urbg.so
libabsl_random_internal_randen.so
libabsl_random_internal_randen_hwaes.so
libabsl_random_internal_randen_hwaes_impl.so
libabsl_random_internal_randen_slow.so
libabsl_random_internal_seed_material.so
libabsl_random_seed_gen_exception.so
libabsl_random_seed_sequences.so
opencv_aipy.egg-info/PKG-INFO
opencv_aipy.egg-info/SOURCES.txt
opencv_aipy.egg-info/dependency_links.txt
opencv_aipy.egg-info/requires.txt
opencv_aipy.egg-info/top_level.txt